ngrid/__init__.py
ngrid/base.py
ngrid/cheb.py
ngrid/equidist.py
ngrid/exceptions.py
ngrid/interpol.py
ngrid/utils.py
tests/__init__.py
tests/test_cheb.py
tests/test_equidist.py
tests/test_interpol.py
tests/test_utils.py
ngrid-0.0.1.dist-info/METADATA
ngrid-0.0.1.dist-info/WHEEL
ngrid-0.0.1.dist-info/top_level.txt
ngrid-0.0.1.dist-info/RECORD
