Metadata-Version: 2.1
Name: ngrid
Version: 0.0.1
Summary: A Python package for numerical computation on grids.
Home-page: UNKNOWN
Author: Matthias Baer
Author-email: matthias.r.baer@googlemail.com
License: None
Platform: ALL
Classifier: Operating System :: OS Independent
Classifier: Programming Language :: Python :: 3
Requires-Python: >=3.6
Requires-Dist: sphinx
